wandbfsspec/__init__.py
wandbfsspec/core.py
wandbfsspec/py.typed
wandbfsspec/spec.py
wandbfsspec-0.2.0.dist-info/entry_points.txt
wandbfsspec-0.2.0.dist-info/LICENSE
wandbfsspec-0.2.0.dist-info/WHEEL
wandbfsspec-0.2.0.dist-info/METADATA
wandbfsspec-0.2.0.dist-info/RECORD
