Metadata-Version: 2.1
Name: wandbfsspec
Version: 0.2.0
Summary: fsspec interface for Weights & Biases (wandb)
Home-page: https://github.com/alvarobartt/wandbfsspec
License: MIT
Author: Alvaro Bartolome
Author-email: alvarobartt@yahoo.com
Requires-Python: >=3.7,<3.10
Classifier: License :: OSI Approved :: MIT License
Classifier: Programming Language :: Python :: 3
Classifier: Programming Language :: Python :: 3.7
Classifier: Programming Language :: Python :: 3.8
Classifier: Programming Language :: Python :: 3.9
Requires-Dist: fsspec (>=2022.5.0,<2023.0.0)
Requires-Dist: wandb (>=0.13.3,<0.14.0)
Project-URL: Documentation, https://github.com/alvarobartt/wandbfsspec
Project-URL: Repository, https://github.com/alvarobartt/wandbfsspec
